qpmpc_layers/__init__.py
qpmpc_layers/exceptions.py
qpmpc_layers/plants.py
qpmpc_layers/qplayer.py
qpmpc_layers/utils.py
qpmpc_layers/integration/__init__.py
qpmpc_layers/integration/start.py
qpmpc_layers/integration/step.py
qpmpc_layers/lti/__init__.py
qpmpc_layers/lti/integrator.py
qpmpc_layers/lti/optimal_control_problem.py
qpmpc_layers/optimal_control/__init__.py
qpmpc_layers/optimal_control/start.py
qpmpc_layers/optimal_control/step.py
qpmpc_layers/optimal_control/terminate.py
qpmpc_layers/optimal_control/wrap.py
qpmpc_layers/types/__init__.py
qpmpc_layers/types/constraint.py
qpmpc_layers/types/dynamics.py
qpmpc_layers/types/integration_map.py
qpmpc_layers/types/qp.py
qpmpc_layers/types/stage_cost.py
qpmpc_layers/types/terminal_cost.py
qpmpc_layers-0.0.1.dist-info/LICENSE
qpmpc_layers-0.0.1.dist-info/WHEEL
qpmpc_layers-0.0.1.dist-info/METADATA
qpmpc_layers-0.0.1.dist-info/RECORD
