Metadata-Version: 2.1
Name: qpmpc_layers
Version: 0.0.1
Summary: Differentiable linear model predictive control in Python.
Keywords: differentiable,model,predictive,control,linear,time-varying
Author-email: Stéphane Caron <stephane.caron@inria.fr>, Valentin Tordjman--Levavasseur <valentin.tordjman-levavasseur@inria.fr>
Maintainer-email: Stéphane Caron <stephane.caron@normalesup.org>
Requires-Python: >=3.9
Classifier: Development Status :: 3 - Alpha
Classifier: Intended Audience :: Developers
Classifier: Intended Audience :: Science/Research
Classifier: License :: OSI Approved :: Apache Software License
Classifier: Operating System :: OS Independent
Classifier: Programming Language :: Python :: 3.9
Classifier: Programming Language :: Python :: 3.10
Classifier: Programming Language :: Python :: 3.11
Classifier: Programming Language :: Python :: 3.12
Classifier: Topic :: Scientific/Engineering
Requires-Dist: proxsuite >=0.6.1
Requires-Dist: qpsolvers >=1.8.0
Requires-Dist: torch >=2.4.1
